[{"id":"2806e615-3895-46d9-8401-0600c91398c9","name":"Skyble","description":"Nondisp fx of nk of 1st MC bone, unsp hand, init for opn fx","latitude":55.6024656,"longitude":31.1754015,"imageUrl":"http://dummyimage.com/100x100.jpg/dddddd/000000"},
{"id":"e7bc2556-72ae-4e95-8394-62c8e9df3e77","name":"Topiczoom","description":"Poisoning by other topical agents, undetermined, subs encntr","latitude":-7.5363189,"longitude":108.4038672,"imageUrl":"http://dummyimage.com/100x100.jpg/ff4444/ffffff"},
{"id":"4682a0be-1409-4bce-b249-910e649a612a","name":"Twitterbeat","description":"Occup of bus injured in collision w ped/anml in traf","latitude":3.6130855,"longitude":96.9182301,"imageUrl":"http://dummyimage.com/100x100.jpg/ff4444/ffffff"},
{"id":"9748d128-5f66-4888-b58a-e8a1f93f1d5e","name":"Snaptags","description":"Oth injury of axillary or brachial vein, unspecified side","latitude":41.634449,"longitude":22.4665446,"imageUrl":"http://dummyimage.com/100x100.jpg/cc0000/ffffff"},
{"id":"96fcf1d0-8d37-4ae0-80ef-c9219c43a1ca","name":"Devbug","description":"Disp fx of nk of r rad, 7thR","latitude":14.960458,"longitude":120.755354,"imageUrl":"http://dummyimage.com/100x100.jpg/dddddd/000000"},
{"id":"1cd58406-ea07-4d42-b1ea-c9a150576a38","name":"Minyx","description":"Disp fx of greater trochanter of r femr, 7thG","latitude":-6.7728847,"longitude":110.816549,"imageUrl":"http://dummyimage.com/100x100.jpg/ff4444/ffffff"},
{"id":"36aa0350-a245-4f09-9a63-4a451ccd2de6","name":"Flipopia","description":"Listerial meningitis and meningoencephalitis","latitude":57.0408915,"longitude":24.0131821,"imageUrl":"http://dummyimage.com/100x100.jpg/dddddd/000000"},
{"id":"837ff980-b74e-49fc-b39d-4e62151e1748","name":"Linkbuzz","description":"Sleep related leg cramps","latitude":49.794097,"longitude":12.5783985,"imageUrl":"http://dummyimage.com/100x100.jpg/ff4444/ffffff"},
{"id":"57b07462-7081-4302-9f09-1b991becefc9","name":"Voonte","description":"Nondisp fx of l tibial tuberosity, 7thD","latitude":6.4482939,"longitude":101.8107351,"imageUrl":"http://dummyimage.com/100x100.jpg/5fa2dd/ffffff"},
{"id":"8d86bd31-10fe-4115-a872-767390b3bccc","name":"Gigaclub","description":"Displaced Rolando's fracture, right hand","latitude":33.277232,"longitude":35.578235,"imageUrl":"http://dummyimage.com/100x100.jpg/dddddd/000000"},
{"id":"c58cb08e-5c12-4e93-b113-0e5621b8926c","name":"Feednation","description":"Unsp fracture of right foot, subs for fx w routn heal","latitude":4.842716,"longitude":7.8558357,"imageUrl":"http://dummyimage.com/100x100.jpg/5fa2dd/ffffff"},
{"id":"e43c6ee6-4a2e-4646-b2cb-78f31ffd8268","name":"Brightdog","description":"Poisn by keratolyt/keratplst/hair trmt drug, assault, subs","latitude":52.5093,"longitude":52.0675,"imageUrl":"http://dummyimage.com/100x100.jpg/ff4444/ffffff"},
{"id":"e70c9927-c65a-440b-a9f7-94a0283b0b00","name":"Trilia","description":"Pauciarticular juvenile rheumatoid arthritis, right knee","latitude":9.7375987,"longitude":8.8087151,"imageUrl":"http://dummyimage.com/100x100.jpg/5fa2dd/ffffff"},
{"id":"87419cd3-374b-4123-a5a2-825e629eb1b9","name":"Innojam","description":"Dislocation of tarsometatarsal joint of unsp foot, init","latitude":9.0835262,"longitude":-79.2906747,"imageUrl":"http://dummyimage.com/100x100.jpg/dddddd/000000"},
{"id":"9f16dfca-444b-4dc4-8a7b-4e9e00eb28b8","name":"Thoughtbeat","description":"Oth physl fx low end rad, r arm, subs for fx w delay heal","latitude":-7.0251813,"longitude":111.3202736,"imageUrl":"http://dummyimage.com/100x100.jpg/ff4444/ffffff"},
{"id":"e26d96da-2d30-49c5-aedb-8e455bbdf2be","name":"Wikizz","description":"Fx unsp metatarsal bone(s), l foot, subs for fx w routn heal","latitude":41.1059592,"longitude":-8.2213311,"imageUrl":"http://dummyimage.com/100x100.jpg/cc0000/ffffff"},
{"id":"7469e9be-f96d-49c5-bddc-8a81f9c65a74","name":"Kwilith","description":"Retained (old) magnetic fb in post wall of globe, right eye","latitude":49.0757178,"longitude":107.0295809,"imageUrl":"http://dummyimage.com/100x100.jpg/ff4444/ffffff"},
{"id":"a4abb124-7456-45e4-8093-dd4a2cb8541e","name":"Yacero","description":"Greenstick fracture of shaft of humerus, unsp arm, sequela","latitude":-34.9284989,"longitude":138.6007456,"imageUrl":"http://dummyimage.com/100x100.jpg/cc0000/ffffff"},
{"id":"9174aeb0-3eaf-4bee-b418-ead99bb0f1e9","name":"Pixope","description":"Toxic effect of insecticides, intentional self-harm, sequela","latitude":-8.5314465,"longitude":118.7780987,"imageUrl":"http://dummyimage.com/100x100.jpg/cc0000/ffffff"},
{"id":"ab3f04f1-4968-4e0b-bf2c-3901767db2b3","name":"Topicblab","description":"Nondisp fx of distal phalanx of unspecified thumb, sequela","latitude":46.798163,"longitude":134.013872,"imageUrl":"http://dummyimage.com/100x100.jpg/dddddd/000000"},
{"id":"459d0c53-648b-42ba-849a-98b951c29dfc","name":"Devpoint","description":"Unspecified injury of deep palmar arch of left hand","latitude":45.416456,"longitude":-73.9160797,"imageUrl":"http://dummyimage.com/100x100.jpg/ff4444/ffffff"},
{"id":"5b95bd20-d64c-414a-be63-7fff584e1952","name":"Skipfire","description":"Unsp injury of ulnar artery at wrs/hnd lv of right arm, subs","latitude":48.8952384,"longitude":2.238154,"imageUrl":"http://dummyimage.com/100x100.jpg/ff4444/ffffff"},
{"id":"fb05d6eb-155d-43de-9789-3abe6f3c1ca8","name":"Dabvine","description":"Stress fracture, unsp foot, subs for fx w routn heal","latitude":43.8234396,"longitude":17.5393153,"imageUrl":"http://dummyimage.com/100x100.jpg/5fa2dd/ffffff"},
{"id":"1563f784-ce03-4fe3-9bda-698db3436791","name":"Tambee","description":"Toxic effects of benzene","latitude":39.4591,"longitude":-8.6671695,"imageUrl":"http://dummyimage.com/100x100.jpg/5fa2dd/ffffff"},
{"id":"ebd648ed-f299-413f-9a6c-83493f1317fa","name":"Kimia","description":"Primary open-angle glaucoma, left eye, indeterminate stage","latitude":24.248501,"longitude":102.159264,"imageUrl":"http://dummyimage.com/100x100.jpg/ff4444/ffffff"},
{"id":"0365b41e-db41-40e0-98d5-4a374e8674a0","name":"Tagpad","description":"Spasm of accommodation, left eye","latitude":-7.543398,"longitude":110.822966,"imageUrl":"http://dummyimage.com/100x100.jpg/dddddd/000000"},
{"id":"09a520bf-c2b3-4966-bba8-594b469e8bcd","name":"Dabjam","description":"Encounter for desensitization to allergens","latitude":-6.2277509,"longitude":106.7092723,"imageUrl":"http://dummyimage.com/100x100.jpg/cc0000/ffffff"},
{"id":"01ad6c41-d74b-492d-9cbb-957d88587853","name":"Eazzy","description":"Prsn brd/alit pk-up/van injured in clsn w ped/anml, sequela","latitude":40.6282676,"longitude":24.5762096,"imageUrl":"http://dummyimage.com/100x100.jpg/cc0000/ffffff"},
{"id":"7798f2a8-cdc1-49bc-9a07-34deeed12bd8","name":"Tazzy","description":"Toxic effect of taipan venom, assault, initial encounter","latitude":35.3,"longitude":25,"imageUrl":"http://dummyimage.com/100x100.jpg/ff4444/ffffff"},
{"id":"d306cc37-0c1d-4763-9006-35b3eb9397a1","name":"Viva","description":"Nondisp fx of capitate bone, unsp wrs, 7thK","latitude":53.5234017,"longitude":27.8299056,"imageUrl":"http://dummyimage.com/100x100.jpg/dddddd/000000"},
{"id":"4be43c0f-b687-42f4-a93b-04272cb8a37c","name":"Topicstorm","description":"Displ oblique fx shaft of l femr, 7thD","latitude":22.396428,"longitude":114.109497,"imageUrl":"http://dummyimage.com/100x100.jpg/5fa2dd/ffffff"},
{"id":"40521f0d-4628-4587-a388-333d80077954","name":"Mudo","description":"Other articular cartilage disorders, right ankle","latitude":29.574103,"longitude":106.537605,"imageUrl":"http://dummyimage.com/100x100.jpg/dddddd/000000"},
{"id":"ed0478f4-0184-459e-83f5-8510b1884156","name":"Ntag","description":"Sprain of unspecified ligament of right ankle, sequela","latitude":10.4825247,"longitude":105.4771084,"imageUrl":"http://dummyimage.com/100x100.jpg/ff4444/ffffff"},
{"id":"cebf1fb6-1191-4ea6-a0d3-e10369948139","name":"Tagtune","description":"Oth intraoperative complications of eye and adnexa, NEC","latitude":31.6360346,"longitude":106.5886373,"imageUrl":"http://dummyimage.com/100x100.jpg/cc0000/ffffff"},
{"id":"e799548b-def3-4596-bdb1-904b22ac3591","name":"Skaboo","description":"Sltr-haris Type I physl fx lower end of unsp fibula, sequela","latitude":52.3140368,"longitude":19.4070384,"imageUrl":"http://dummyimage.com/100x100.jpg/ff4444/ffffff"},
{"id":"031faa6f-53c0-4d0f-8ca5-ac93aeb2c151","name":"Katz","description":"Oth disorders of skin, subcu, not elsewhere classified","latitude":34.705306,"longitude":108.438067,"imageUrl":"http://dummyimage.com/100x100.jpg/cc0000/ffffff"},
{"id":"d3615bfe-60c1-444c-a8ab-4eaa49fe14b2","name":"Pixope","description":"Oth malignant neoplasm of skin of lower limb, including hip","latitude":56.4177803,"longitude":21.8525134,"imageUrl":"http://dummyimage.com/100x100.jpg/cc0000/ffffff"},
{"id":"ccacbc01-a6a0-46a8-aaef-2f8ebf61e246","name":"Voonix","description":"Non-institutional (private) residence as place","latitude":-3.1914976,"longitude":140.8872648,"imageUrl":"http://dummyimage.com/100x100.jpg/cc0000/ffffff"},
{"id":"15da2d2a-7607-4a01-9488-b07921f61ff7","name":"Vinder","description":"Toxic effect of corrosive organic compounds, undet, sequela","latitude":40.6892276,"longitude":-8.6031905,"imageUrl":"http://dummyimage.com/100x100.jpg/dddddd/000000"},
{"id":"092e74f6-8afb-47ba-ba94-0d217b06c282","name":"Kwinu","description":"Oth injury of popliteal artery, unspecified leg, sequela","latitude":-14.0993396,"longitude":-75.6891699,"imageUrl":"http://dummyimage.com/100x100.jpg/ff4444/ffffff"},
{"id":"837e3479-97b9-47b8-a93c-59e4485566ff","name":"Buzzshare","description":"Fall in (into) filled bathtub causing other injury, sequela","latitude":5.9779631,"longitude":-0.0886948,"imageUrl":"http://dummyimage.com/100x100.jpg/cc0000/ffffff"},
{"id":"c95cc636-07f7-4420-856f-178d80124911","name":"Meevee","description":"Sltr-haris Type I physeal fracture of right metatarsal, 7thD","latitude":-22.8262707,"longitude":-43.0152252,"imageUrl":"http://dummyimage.com/100x100.jpg/5fa2dd/ffffff"},
{"id":"dfca4848-faec-4329-8c09-e402a0463670","name":"Bubbletube","description":"Displ Maisonneuve's fx unsp leg, 7thG","latitude":58.7239855,"longitude":59.4504627,"imageUrl":"http://dummyimage.com/100x100.jpg/ff4444/ffffff"},
{"id":"8ceda0e6-d0ab-49e4-9cc8-51c5ddb61f2d","name":"Realbuzz","description":"Toxoplasma myositis","latitude":49.9211825,"longitude":19.4250873,"imageUrl":"http://dummyimage.com/100x100.jpg/dddddd/000000"},
{"id":"31e3e877-2613-4d66-b36c-cefd2722e1f5","name":"Zooveo","description":"Corrosion of second degree of unspecified ear, sequela","latitude":49.5207147,"longitude":23.2065501,"imageUrl":"http://dummyimage.com/100x100.jpg/ff4444/ffffff"},
{"id":"d6dff7ce-7e98-4c49-a3cf-abd5a85e94f2","name":"Dabtype","description":"Mast cell leukemia","latitude":-6.831959,"longitude":107.0805202,"imageUrl":"http://dummyimage.com/100x100.jpg/cc0000/ffffff"},
{"id":"3191a247-4564-43d1-9de9-dbf2143b3a28","name":"Muxo","description":"Complete traumatic amputation of unsp ear, init encntr","latitude":-6.9871199,"longitude":107.8487279,"imageUrl":"http://dummyimage.com/100x100.jpg/dddddd/000000"},
{"id":"3558f7eb-bceb-4fe3-8f46-a28c0d915a36","name":"Divanoodle","description":"Low-tension glaucoma, unspecified eye, mild stage","latitude":5.9630513,"longitude":10.1591213,"imageUrl":"http://dummyimage.com/100x100.jpg/5fa2dd/ffffff"},
{"id":"bb2afaa1-8609-4783-8e8e-dbaa0f4aa365","name":"Dynabox","description":"Unspecified Zone II fracture of sacrum","latitude":56.2086482,"longitude":95.4511119,"imageUrl":"http://dummyimage.com/100x100.jpg/dddddd/000000"},
{"id":"62e26f7d-cf92-443a-b909-09c3088a7da4","name":"Livepath","description":"Flail chest","latitude":25.073688,"longitude":121.5140449,"imageUrl":"http://dummyimage.com/100x100.jpg/dddddd/000000"},
{"id":"fcf3c6b3-94cd-4f02-b177-14f4beed580e","name":"Topicshots","description":"Ulnohumeral (joint) sprain of left elbow, initial encounter","latitude":46.5670711,"longitude":15.9429753,"imageUrl":"http://dummyimage.com/100x100.jpg/dddddd/000000"},
{"id":"26c0862c-573a-4a33-8f85-e76402412a3f","name":"Quinu","description":"Mood disorder due to known physiol cond w depressv features","latitude":-8.2272033,"longitude":111.3679689,"imageUrl":"http://dummyimage.com/100x100.jpg/dddddd/000000"},
{"id":"5d46ee7e-b01e-4d67-8196-66895bf74302","name":"Fiveclub","description":"Insect bite (nonvenomous), unspecified hip, init encntr","latitude":10.9466832,"longitude":123.3577849,"imageUrl":"http://dummyimage.com/100x100.jpg/dddddd/000000"},
{"id":"f7c019e2-f54b-4c58-86a4-f4c9a42ddeb4","name":"Skidoo","description":"Pathological fracture, pelvis, subs for fx w malunion","latitude":-6.3323352,"longitude":105.8671954,"imageUrl":"http://dummyimage.com/100x100.jpg/dddddd/000000"},
{"id":"eacdab44-91d7-4421-951e-5d99e0fcab90","name":"Jabbercube","description":"Angioneurotic edema","latitude":43.438342,"longitude":126.330439,"imageUrl":"http://dummyimage.com/100x100.jpg/dddddd/000000"},
{"id":"b1f0c3c6-8c2f-473b-b8a3-9ac81825acb8","name":"Tazzy","description":"Nondisp commnt suprcndl fx w/o intrcndl fx r humer, 7thB","latitude":14.6632212,"longitude":-90.6132158,"imageUrl":"http://dummyimage.com/100x100.jpg/dddddd/000000"},
{"id":"520895e6-416a-40f2-a446-d20562530295","name":"Gabtune","description":"Contact with electric knife, subsequent encounter","latitude":-6.576574,"longitude":111.0683954,"imageUrl":"http://dummyimage.com/100x100.jpg/5fa2dd/ffffff"},
{"id":"528fb51c-5884-422c-9266-1876c005bbea","name":"Devshare","description":"Disp fx of posterior column of left acetabulum, sequela","latitude":33.025433,"longitude":119.020584,"imageUrl":"http://dummyimage.com/100x100.jpg/cc0000/ffffff"},
{"id":"cd51b17f-ea1c-4f6c-9b0c-d1204bd5d011","name":"Photobug","description":"Oth fx upr and low end unsp fibula, init for opn fx type I/2","latitude":48.5202109,"longitude":3.6973504,"imageUrl":"http://dummyimage.com/100x100.jpg/ff4444/ffffff"},
{"id":"5022081d-4b2e-469c-86c6-a47f81967fc9","name":"Feedfire","description":"Prsn brd/alit from bus injured in collision w hv veh, subs","latitude":29.655143,"longitude":121.406995,"imageUrl":"http://dummyimage.com/100x100.jpg/5fa2dd/ffffff"},
{"id":"f70a2110-8c71-4ff3-b972-7ae163796923","name":"Katz","description":"Open bite of left lesser toe(s) w/o damage to nail, subs","latitude":46.0029454,"longitude":14.0278459,"imageUrl":"http://dummyimage.com/100x100.jpg/dddddd/000000"},
{"id":"e8ec0091-77ac-4c82-8e61-29d013f4f1bb","name":"Avamba","description":"Herpesviral ocular disease","latitude":14.5679735,"longitude":121.0210496,"imageUrl":"http://dummyimage.com/100x100.jpg/5fa2dd/ffffff"},
{"id":"b7e87c99-1187-4c1a-a7ea-762fcc6e5e0b","name":"Quamba","description":"Laceration of bladder","latitude":55.612118,"longitude":-2.7795629,"imageUrl":"http://dummyimage.com/100x100.jpg/cc0000/ffffff"},
{"id":"d87e6718-3589-4225-90de-5a38e27d80fc","name":"Zoombeat","description":"Path fracture in neoplastic disease, unsp humerus, sequela","latitude":49.7692372,"longitude":43.6416286,"imageUrl":"http://dummyimage.com/100x100.jpg/5fa2dd/ffffff"},
{"id":"c321c1cc-cce5-4e5a-9e23-a4a481fa1088","name":"Trilia","description":"Trigger finger, right index finger","latitude":46.1854516,"longitude":30.3414908,"imageUrl":"http://dummyimage.com/100x100.jpg/dddddd/000000"},
{"id":"b4cf7f34-ab1c-40c5-9c5c-126d1d3d7cb9","name":"Skynoodle","description":"Stress fracture, oth site, subs for fx w delay heal","latitude":1.3350205,"longitude":34.3976356,"imageUrl":"http://dummyimage.com/100x100.jpg/cc0000/ffffff"},
{"id":"257ffb79-4503-4ee8-ad1e-e56bf63e284a","name":"Jabberbean","description":"Corrosion of second degree of right toe(s) (nail), sequela","latitude":39.5421345,"longitude":-118.5736924,"imageUrl":"http://dummyimage.com/100x100.jpg/5fa2dd/ffffff"},
{"id":"7397dfd2-8d98-4e76-88e2-df6444bac162","name":"Browsetype","description":"Chronic lacrimal canaliculitis of bi lacrimal passages","latitude":34.933333,"longitude":9.2,"imageUrl":"http://dummyimage.com/100x100.jpg/ff4444/ffffff"},
{"id":"368a598c-f1ca-4fd3-93af-feb1df78f675","name":"InnoZ","description":"Injury of digital nerve of right middle finger","latitude":31.352859,"longitude":118.432941,"imageUrl":"http://dummyimage.com/100x100.jpg/ff4444/ffffff"},
{"id":"f54b6613-fce4-4f16-a09c-e8678b1095fa","name":"Demivee","description":"Salter-Harris Type II physeal fracture of l calcaneus, 7thK","latitude":8.4297819,"longitude":-82.8317486,"imageUrl":"http://dummyimage.com/100x100.jpg/cc0000/ffffff"},
{"id":"b10a4d07-8d5f-46ad-9437-db1b9ac02268","name":"Gigaclub","description":"Dx and monitoring gen hosp/persnl-use devices assoc w incdt","latitude":26.695419,"longitude":101.841707,"imageUrl":"http://dummyimage.com/100x100.jpg/5fa2dd/ffffff"},
{"id":"f34f3437-5138-49ba-b055-15ce86908c85","name":"Dazzlesphere","description":"Hypogalactia","latitude":42.1636682,"longitude":20.1893997,"imageUrl":"http://dummyimage.com/100x100.jpg/ff4444/ffffff"},
{"id":"d81b2f7d-4003-4e37-b080-f725686250a5","name":"Trilith","description":"Person outside bus inj in clsn w rail trn/veh in traf, init","latitude":15.5835978,"longitude":102.4253001,"imageUrl":"http://dummyimage.com/100x100.jpg/ff4444/ffffff"},
{"id":"ef081004-cffe-4e33-a0db-539c807552c1","name":"Zoonder","description":"Deformity of orbit","latitude":53.4431223,"longitude":30.9995629,"imageUrl":"http://dummyimage.com/100x100.jpg/5fa2dd/ffffff"},
{"id":"51ec8cfd-6e1f-4e3f-a4ec-c7fc2a9df993","name":"Fivebridge","description":"Burn of third degree of left foot, sequela","latitude":-2.631564,"longitude":140.470795,"imageUrl":"http://dummyimage.com/100x100.jpg/cc0000/ffffff"},
{"id":"8b85f066-7dfd-46f5-8c2a-fd4ab4f6bac7","name":"Kwimbee","description":"Osteopathy in diseases classified elsewhere, unsp shoulder","latitude":39.7494186,"longitude":-7.9233898,"imageUrl":"http://dummyimage.com/100x100.jpg/ff4444/ffffff"},
{"id":"30dca70b-5250-4b43-9172-c2037fc46746","name":"Camimbo","description":"Chronic nephritic syndrome with dense deposit disease","latitude":-8.2981893,"longitude":31.5227266,"imageUrl":"http://dummyimage.com/100x100.jpg/5fa2dd/ffffff"},
{"id":"2946792b-2058-4d01-96b7-a4375b5fbea9","name":"Brightdog","description":"Oth mult gest, unab to dtrm num plcnta & amnio sacs, 2nd tri","latitude":-7.5085719,"longitude":-35.3126181,"imageUrl":"http://dummyimage.com/100x100.jpg/cc0000/ffffff"},
{"id":"3a874f20-dede-410a-8945-9cf5aec3b448","name":"Abata","description":"Puncture wound without foreign body of right shoulder","latitude":22.3179093,"longitude":-79.6558242,"imageUrl":"http://dummyimage.com/100x100.jpg/cc0000/ffffff"},
{"id":"88cc4cd6-4892-413a-a004-76624b6cb3b6","name":"Zoomlounge","description":"Necrotizing vasculopathy, unspecified","latitude":7.3832138,"longitude":122.804355,"imageUrl":"http://dummyimage.com/100x100.jpg/dddddd/000000"},
{"id":"5651652a-9599-49b8-b5ef-d47eacc99f16","name":"Skimia","description":"Mech compl of unsp card and vasc devices and implnt, sequela","latitude":-14.116667,"longitude":-73.616667,"imageUrl":"http://dummyimage.com/100x100.jpg/ff4444/ffffff"},
{"id":"ae2c0183-40bd-40b6-8d79-4408e23ed1dc","name":"Kaymbo","description":"Foreign body granuloma of soft tissue, NEC, thigh","latitude":46.8515406,"longitude":40.3138699,"imageUrl":"http://dummyimage.com/100x100.jpg/cc0000/ffffff"},
{"id":"a100c49c-7bf7-459d-9a94-fe51badfbaf0","name":"Demizz","description":"Acute nonspecific idiopathic pericarditis","latitude":28.777526,"longitude":87.253343,"imageUrl":"http://dummyimage.com/100x100.jpg/dddddd/000000"},
{"id":"9f554bac-dcc2-48f8-82c0-0cb8993c95bb","name":"Vidoo","description":"Minor laceration of femoral artery, left leg, sequela","latitude":49.059828,"longitude":6.154795,"imageUrl":"http://dummyimage.com/100x100.jpg/cc0000/ffffff"},
{"id":"497b14da-e83e-44a4-b1f0-98bee904bcd5","name":"Realmix","description":"Tear of unspecified meniscus, current injury","latitude":27.820107,"longitude":105.965695,"imageUrl":"http://dummyimage.com/100x100.jpg/cc0000/ffffff"},
{"id":"ec467fa0-a7ae-4f55-a0ef-39844604107b","name":"Meejo","description":"Labor and delivery complicated by other cord complications","latitude":17.5358596,"longitude":121.6851715,"imageUrl":"http://dummyimage.com/100x100.jpg/ff4444/ffffff"},
{"id":"068fdbb6-d1a8-44d5-91e2-0c3103326698","name":"Eazzy","description":"War op involving unsp explosn and fragments, civilian, subs","latitude":-34.6507337,"longitude":-58.4114593,"imageUrl":"http://dummyimage.com/100x100.jpg/5fa2dd/ffffff"},
{"id":"db92904f-5084-41ae-8636-3b121b9fd9e1","name":"Divavu","description":"Displaced fracture of proximal phalanx of finger","latitude":6.6650328,"longitude":159.7540106,"imageUrl":"http://dummyimage.com/100x100.jpg/cc0000/ffffff"},
{"id":"bc8bd2ab-14d7-4d3c-9ea9-e4168f763788","name":"Linklinks","description":"Nondisp transverse fx r patella, 7thJ","latitude":33.4316535,"longitude":131.3529666,"imageUrl":"http://dummyimage.com/100x100.jpg/cc0000/ffffff"},
{"id":"23352555-398c-45e4-a71e-8787e32447d7","name":"Kazu","description":"Inj axillary or brachial vein, left side, subs encntr","latitude":59.7388394,"longitude":10.1603397,"imageUrl":"http://dummyimage.com/100x100.jpg/ff4444/ffffff"},
{"id":"b6171576-d240-482d-9211-017f64de1b7d","name":"Realmix","description":"Other specified crystal arthropathies, left hip","latitude":-6.7765974,"longitude":-79.8442978,"imageUrl":"http://dummyimage.com/100x100.jpg/ff4444/ffffff"},
{"id":"1d59fb4f-8639-489d-96b8-6e4f1be16af3","name":"Realblab","description":"Corrosion of first degree of unspecified shoulder","latitude":-7.280135,"longitude":112.6347636,"imageUrl":"http://dummyimage.com/100x100.jpg/ff4444/ffffff"},
{"id":"b0078bad-7916-4033-991b-5753e1007d55","name":"Edgepulse","description":"Puncture wound without foreign body of lip, sequela","latitude":38.6580874,"longitude":-8.7698425,"imageUrl":"http://dummyimage.com/100x100.jpg/dddddd/000000"},
{"id":"b7cb2287-03d8-4fb7-92e2-169035d84643","name":"Yombu","description":"Unspecified viral infection of central nervous system","latitude":45.2235244,"longitude":20.0319685,"imageUrl":"http://dummyimage.com/100x100.jpg/cc0000/ffffff"},
{"id":"49492d17-9d38-4441-ae33-2dd32c343897","name":"Npath","description":"Unsp open wound of unsp eyelid and periocular area, init","latitude":24.410255,"longitude":117.416058,"imageUrl":"http://dummyimage.com/100x100.jpg/5fa2dd/ffffff"},
{"id":"5fb79b0b-c959-42f3-800b-bae71338d0d6","name":"Skivee","description":"Infections of urethra in pregnancy, second trimester","latitude":23.178828,"longitude":113.297291,"imageUrl":"http://dummyimage.com/100x100.jpg/dddddd/000000"},
{"id":"bd3b6b8a-db63-40e6-8a88-3b42fd24af50","name":"Bubblebox","description":"War op involving explosion due to acc disch of own munit","latitude":14.7008738,"longitude":120.9869405,"imageUrl":"http://dummyimage.com/100x100.jpg/dddddd/000000"},
{"id":"59b4b7f4-f976-4a8f-935a-8b89a63a0f06","name":"Mydeo","description":"Unspecified dislocation of right ring finger, subs encntr","latitude":30.736899,"longitude":84.520832,"imageUrl":"http://dummyimage.com/100x100.jpg/dddddd/000000"},
{"id":"35c98d5c-d770-4bda-ac12-6bd83f916037","name":"Zoomcast","description":"Incomplete rotatr-cuff tear/ruptr of l shoulder, not trauma","latitude":44.7783548,"longitude":19.5985451,"imageUrl":"http://dummyimage.com/100x100.jpg/cc0000/ffffff"},
{"id":"7a871de0-144b-4c24-9e93-e01c8b5cf0fb","name":"Innotype","description":"Drown after fall into bathtub, undetermined intent, sequela","latitude":16.94472,"longitude":104.7229279,"imageUrl":"http://dummyimage.com/100x100.jpg/ff4444/ffffff"}]
